fileadapters/BaseFileAdapter.py
fileadapters/S3Adapter.py
fileadapters/__init__.py
fileadapters/basefileadapter.py
fileadapters/s3adapter.py
formaters/BaseFileFormater.py
formaters/__init__.py
formaters/basefileformater.py
s3adapter-0.6.2.dist-info/METADATA
s3adapter-0.6.2.dist-info/WHEEL
s3adapter-0.6.2.dist-info/top_level.txt
s3adapter-0.6.2.dist-info/RECORD
