Metadata-Version: 2.1
Name: s3adapter
Version: 0.6.2
Summary: A AWS S3 Python Adapter to Readn, Write and Check existence of files in S3 Buckets.
Home-page: UNKNOWN
Author: Flavio Lopes
Author-email: flavio.lopes@ideiasfactory.tech
Maintainer: Ideias Factory
License: MIT
Platform: UNKNOWN
Requires-Dist: boto3 ==1.34.12
Requires-Dist: botocore ==1.34.12
Requires-Dist: jmespath ==1.0.1
Requires-Dist: numpy ==1.26.3
Requires-Dist: pandas ==2.1.4
Requires-Dist: python-dateutil ==2.8.2
Requires-Dist: python-dotenv ==1.0.0
Requires-Dist: pytz ==2023.3.post1
Requires-Dist: s3transfer ==0.10.0
Requires-Dist: six ==1.16.0
Requires-Dist: tzdata ==2023.4
Requires-Dist: urllib3 ==1.26.18
